.gitignore
GNUmakefile
LICENSE.md
MANIFEST.in
NEWS.md
README.md
acefile.py
requirements-dev.txt
requirements.txt
setup.py
.github/workflows/test.yml
acefile.egg-info/PKG-INFO
acefile.egg-info/SOURCES.txt
acefile.egg-info/dependency_links.txt
acefile.egg-info/entry_points.txt
acefile.egg-info/top_level.txt
apidoc/GNUmakefile
apidoc/conf.py
apidoc/index.rst
apidoc/_static/.gitkeep
c/acebitstream.c
c/acebitstream.h
c/acebitstream_mod.c
tests/conftest.py
tests/test_smoke.py